streamlit_firstlanguage/__init__.py
streamlit_firstlanguage/classify.py
streamlit_firstlanguage/imagecaption.py
streamlit_firstlanguage/lemma.py
streamlit_firstlanguage/morph.py
streamlit_firstlanguage/ner.py
streamlit_firstlanguage/postag.py
streamlit_firstlanguage/qa.py
streamlit_firstlanguage/stem.py
streamlit_firstlanguage/summary.py
streamlit_firstlanguage/tableqa.py
streamlit_firstlanguage/translate.py
streamlit_firstlanguage/frontend/build/asset-manifest.json
streamlit_firstlanguage/frontend/build/bootstrap.min.css
streamlit_firstlanguage/frontend/build/index.html
streamlit_firstlanguage/frontend/build/precache-manifest.39682703ad3dc460cfa64a7cc9e7c9a7.js
streamlit_firstlanguage/frontend/build/service-worker.js
streamlit_firstlanguage/frontend/build/static/js/2.df12b593.chunk.js
streamlit_firstlanguage/frontend/build/static/js/2.df12b593.chunk.js.LICENSE.txt
streamlit_firstlanguage/frontend/build/static/js/2.df12b593.chunk.js.map
streamlit_firstlanguage/frontend/build/static/js/main.eb315714.chunk.js
streamlit_firstlanguage/frontend/build/static/js/main.eb315714.chunk.js.map
streamlit_firstlanguage/frontend/build/static/js/runtime-main.9f763134.js
streamlit_firstlanguage/frontend/build/static/js/runtime-main.9f763134.js.map
streamlit_firstlanguage-1.0.2.dist-info/LICENSE
streamlit_firstlanguage-1.0.2.dist-info/METADATA
streamlit_firstlanguage-1.0.2.dist-info/WHEEL
streamlit_firstlanguage-1.0.2.dist-info/top_level.txt
streamlit_firstlanguage-1.0.2.dist-info/RECORD
